jupytercad_gather/__init__.py
jupytercad_gather/_version.py
jupytercad_gather-0.1.0.data/data/share/jupyter/labextensions/jupytercad_gather/package.json
jupytercad_gather-0.1.0.data/data/share/jupyter/labextensions/jupytercad_gather/schemas/jupytercad_gather/package.json.orig
jupytercad_gather-0.1.0.data/data/share/jupyter/labextensions/jupytercad_gather/schemas/jupytercad_gather/plugin.json
jupytercad_gather-0.1.0.data/data/share/jupyter/labextensions/jupytercad_gather/static/543.7275cb1420fa32e6945f.js
jupytercad_gather-0.1.0.data/data/share/jupyter/labextensions/jupytercad_gather/static/714.20b3883ac11db16feb2b.js
jupytercad_gather-0.1.0.data/data/share/jupyter/labextensions/jupytercad_gather/static/728.90febe6caa169ce366e7.js
jupytercad_gather-0.1.0.data/data/share/jupyter/labextensions/jupytercad_gather/static/remoteEntry.49cd2f5637a62706bf9a.js
jupytercad_gather-0.1.0.data/data/share/jupyter/labextensions/jupytercad_gather/static/style.js
jupytercad_gather-0.1.0.data/data/share/jupyter/labextensions/jupytercad_gather/static/third-party-licenses.json
jupytercad_gather-0.1.0.data/data/share/jupyter/labextensions/jupytercad_gather/install.json
jupytercad_gather-0.1.0.dist-info/METADATA
jupytercad_gather-0.1.0.dist-info/WHEEL
jupytercad_gather-0.1.0.dist-info/licenses/LICENSE
jupytercad_gather-0.1.0.dist-info/RECORD
