Metadata-Version: 2.3
Name: jupytercad_gather
Version: 0.1.0
Dynamic: Keywords
Summary: A JupyterCAD plugin for the JupyterLab-Gather extenstion
Project-URL: Homepage, https://github.com/jupytercad/jupytercad-gather
Project-URL: Bug Tracker, https://github.com/jupytercad/jupytercad-gather/issues
Project-URL: Repository, https://github.com/jupytercad/jupytercad-gather.git
Author-email: Greg Mooney <gregory.mooney@quantstack.net>
License: BSD 3-Clause License
License-File: LICENSE
Classifier: Framework :: Jupyter
Classifier: Framework :: Jupyter :: JupyterLab
Classifier: Framework :: Jupyter :: JupyterLab :: 4
Classifier: Framework :: Jupyter :: JupyterLab :: Extensions
Classifier: Framework :: Jupyter :: JupyterLab :: Extensions :: Prebuilt
Classifier: License :: OSI Approved :: BSD License
Classifier: Programming Language :: Python
Classifier: Programming Language :: Python :: 3
Classifier: Programming Language :: Python :: 3.8
Classifier: Programming Language :: Python :: 3.9
Classifier: Programming Language :: Python :: 3.10
Classifier: Programming Language :: Python :: 3.11
Classifier: Programming Language :: Python :: 3.12
Requires-Python: >=3.8
Requires-Dist: jupytercad>=2.0.0a6
Requires-Dist: jupyterlab-gather>=0.1.0
